tools_basics/__init__.py
tools_basics/data_handler.py
tools_basics/helpers.py
tools_basics/visualizer.py
tools_basics-0.1.0.dist-info/METADATA
tools_basics-0.1.0.dist-info/WHEEL
tools_basics-0.1.0.dist-info/top_level.txt
tools_basics-0.1.0.dist-info/RECORD
