Metadata-Version: 2.1
Name: tools_basics
Version: 0.1.0
Summary: A set of tools for the lesson on basics (LLM Course)
Author: Rodion Khvorostov
Author-email: rodion.khvorostov@jetbrains.com
Requires-Python: >=3.10
Requires-Dist: pandas
Requires-Dist: numpy
Requires-Dist: matplotlib
Requires-Dist: datasets
Requires-Dist: omegaconf
Requires-Dist: tabulate
Requires-Dist: bokeh
